<Map>
  <Name>Cinnibar_Island</Name>
  <TileSet>Main/Cinnibar_Island.png</TileSet>
  <MapSize>
    <X>24</X>
    <Y>21</Y>
  </MapSize>
  <TilePixelSize>32</TilePixelSize>
  <UnderLayer>55 55 55 55 55 55 55 55 55 55 55 55 55 55 55 55 55 55 55 55 55 55 55 55 55 55 55 55 55 55 55 55 55 55 55 55 55 55 55 55 55 55 55 55 55 55 55 55 55 55 55 55 55 55 55 55 55 55 55 55 55 55 55 55 55 55 55 55 55 55 55 55 55 55 55 55 55 55 55 55 55 55 55 55 55 55 55 55 55 55 55 55 55 55 55 55 55 55 55 55 55 55 55 55 55 55 55 55 55 55 55 55 55 55 55 55 55 55 55 55 55 55 55 55 55 55 55 55 55 55 55 55 55 55 55 55 55 55 55 55 55 55 55 55 55 55 55 55 55 55 55 55 55 55 55 55 55 55 55 55 55 55 55 55 55 55 55 55 55 55 55 55 55 55 55 55 55 55 55 55 55 55 55 55 55 55 55 55 55 55 55 55 55 55 55 55 55 55 55 55 55 55 55 55 55 55 55 55 55 55 55 55 55 55 55 55 55 55 55 55 55 55 55 55 55 55 55 55 55 55 55 55 55 55 55 55 55 55 55 55 55 55 55 55 55 55 55 55 55 55 55 55 55 55 55 55 55 55 55 55 55 55 55 55 55 55 55 55 55 55 55 55 55 55 55 55 55 55 55 55 55 55 55 55 55 55 55 55 55 55 55 55 55 55 55 55 55 55 55 55 55 55 55 55 55 55 55 55 55 55 55 55 55 55 55 55 55 55 55 55 55 55 55 55 55 55 55 55 55 55 55 55 55 55 55 55 55 55 55 55 55 55 55 55 55 55 55 55 55 55 55 55 55 55 55 55 55 55 55 55 55 55 55 55 55 55 55 55 55 55 55 55 55 55 55 55 55 55 55 55 55 55 55 55 55 55 55 55 55 55 55 55 55 55 55 55 55 55 55 55 55 55 55 55 55 55 55 55 55 55 55 55 55 55 55 55 55 55 55 55 55 55 55 55 55 55 55 55 55 55 55 55 55 55 55 55 55 55 55 55 55 55 55 55 55 55 55 55 55 55 55 55 55 55 55 55 55 55 55 55 55 55 55 55 55 55 55 55 55 55 55 55 55 55 55 55 55 55 55 55 55 55 55 55 55 55 55 55 55 55 55 55 55 55 55 55 55 55 55 55 55 55 55 55 </UnderLayer>
  <BaseLayer>-1 -1 -1 -1 13 15 15 15 15 15 15 15 15 16 33 22 23 23 23 23 23 23 23 90 -1 -1 -1 -1 13 15 15 15 15 15 15 15 346 27 33 33 33 33 33 33 33 33 33 11 -1 -1 -1 -1 13 15 346 26 26 26 26 26 27 44 44 33 33 33 34 34 34 33 33 11 -1 -1 -1 -1 13 15 16 33 33 33 33 34 34 34 34 34 33 33 33 33 34 34 33 11 -1 -1 -1 -1 13 15 16 33 33 33 44 34 44 44 44 33 33 33 34 34 34 33 33 11 -1 -1 -1 -1 13 15 16 33 44 44 44 34 44 44 34 34 33 34 34 33 33 33 33 11 -1 -1 -1 -1 13 15 16 33 44 44 44 34 44 33 34 34 34 33 34 33 33 3 4 11 -1 -1 -1 -1 13 15 16 33 33 44 34 34 34 34 33 33 33 34 34 33 33 14 15 11 -1 -1 -1 -1 13 15 16 33 33 33 44 44 0 0 0 0 0 33 33 33 33 14 15 11 -1 -1 -1 -1 13 15 16 33 33 33 33 33 0 0 0 0 0 34 33 33 33 14 15 11 -1 -1 -1 -1 13 15 16 33 33 33 33 33 0 0 0 0 0 33 33 33 33 14 15 11 -1 -1 -1 -1 13 15 335 4 4 4 4 5 33 33 33 33 33 33 33 33 34 14 15 11 -1 -1 -1 -1 80 1 1 1 2 15 15 16 33 34 34 34 34 34 34 34 34 14 15 11 -1 -1 -1 -1 -1 -1 -1 -1 13 15 15 335 4 4 4 4 4 4 4 4 4 334 15 11 -1 -1 -1 -1 -1 -1 -1 -1 13 15 15 15 15 15 15 15 15 15 15 15 15 15 15 11 -1 -1 -1 -1 -1 -1 -1 -1 80 1 1 1 1 1 1 1 1 1 1 1 1 1 1 79 -1 -1 -1 -1 -1 -1 -1 -1 -1 -1 -1 -1 -1 -1 -1 -1 -1 -1 -1 -1 -1 -1 -1 -1 -1 -1 -1 -1 -1 -1 -1 -1 -1 -1 -1 -1 -1 -1 -1 -1 -1 -1 -1 -1 -1 -1 -1 -1 -1 -1 -1 -1 -1 -1 -1 -1 -1 -1 -1 -1 -1 -1 -1 -1 -1 -1 -1 -1 -1 -1 -1 -1 -1 -1 -1 -1 -1 -1 -1 -1 -1 -1 -1 -1 -1 -1 -1 -1 -1 -1 -1 -1 -1 -1 -1 -1 -1 -1 -1 -1 -1 -1 -1 -1 -1 -1 -1 -1 -1 -1 -1 -1 -1 -1 -1 -1 -1 -1 -1 -1 </BaseLayer>
  <MiddleLayer>35 36 -1 -1 -1 99 100 101 102 103 104 105 -1 -1 -1 -1 -1 -1 -1 -1 -1 -1 -1 -1 46 47 -1 -1 -1 110 111 112 113 114 115 116 -1 -1 -1 -1 -1 165 166 167 168 169 171 -1 35 36 -1 -1 -1 121 122 123 124 125 126 127 -1 -1 -1 -1 -1 176 177 178 179 180 182 -1 46 47 -1 -1 -1 132 133 134 135 136 137 138 6 -1 -1 -1 -1 187 188 189 190 191 193 -1 -1 35 36 -1 -1 143 144 145 146 147 148 149 -1 -1 -1 -1 -1 198 199 200 201 202 204 -1 -1 46 47 -1 -1 -1 -1 -1 -1 -1 -1 -1 -1 -1 -1 -1 -1 -1 -1 -1 -1 -1 28 -1 -1 35 36 -1 -1 -1 -1 -1 -1 -1 -1 -1 -1 -1 -1 -1 -1 -1 -1 -1 -1 -1 -1 -1 -1 46 47 -1 -1 220 221 222 223 224 225 226 0 0 0 0 0 -1 -1 -1 -1 -1 -1 -1 35 36 -1 -1 -1 231 232 233 234 235 236 237 264 265 266 267 268 -1 -1 -1 -1 -1 -1 -1 46 47 -1 -1 -1 242 243 244 245 246 247 248 275 276 277 278 279 319 320 321 322 -1 -1 -1 35 36 -1 -1 -1 6 -1 -1 -1 -1 -1 -1 286 287 288 289 290 330 331 332 333 -1 -1 -1 46 47 -1 -1 -1 -1 -1 -1 -1 -1 -1 -1 297 298 299 300 301 341 342 343 344 -1 -1 -1 -1 35 36 -1 -1 -1 -1 -1 -1 -1 -1 -1 -1 -1 -1 -1 -1 -1 -1 -1 -1 -1 -1 -1 -1 46 47 -1 -1 -1 -1 -1 -1 -1 -1 -1 -1 -1 -1 -1 -1 -1 -1 -1 -1 -1 -1 -1 -1 35 36 -1 -1 -1 -1 -1 -1 -1 -1 -1 -1 -1 -1 -1 -1 -1 -1 -1 -1 -1 -1 -1 78 46 47 -1 -1 -1 -1 -1 -1 -1 -1 -1 -1 -1 -1 -1 -1 -1 -1 -1 -1 -1 -1 -1 81 -1 35 36 -1 -1 -1 -1 -1 -1 -1 -1 -1 -1 -1 -1 -1 -1 -1 -1 -1 -1 -1 -1 81 -1 46 47 35 36 35 36 -1 -1 -1 -1 -1 -1 35 36 35 36 35 36 -1 -1 -1 -1 81 78 -1 -1 46 47 46 47 35 36 35 36 35 36 46 47 46 47 46 47 35 36 35 36 81 81 81 81 81 78 -1 -1 46 47 46 47 46 47 -1 77 81 81 78 -1 46 47 46 47 81 81 81 81 81 81 81 81 81 81 81 81 81 81 81 81 81 81 81 81 81 81 81 81 </MiddleLayer>
  <TopLayer>-1 -1 -1 -1 -1 -1 -1 -1 -1 -1 -1 -1 -1 -1 -1 -1 -1 154 155 156 158 159 160 -1 -1 -1 -1 -1 -1 -1 -1 -1 -1 -1 -1 -1 -1 -1 -1 -1 -1 -1 -1 -1 -1 -1 -1 -1 -1 -1 -1 -1 -1 -1 -1 -1 -1 -1 -1 -1 -1 -1 -1 -1 -1 -1 -1 -1 -1 -1 -1 -1 -1 -1 -1 -1 -1 -1 -1 -1 -1 -1 -1 -1 -1 -1 -1 -1 -1 -1 -1 -1 -1 -1 -1 -1 -1 -1 -1 -1 -1 -1 -1 -1 -1 -1 -1 -1 -1 -1 -1 -1 -1 -1 -1 -1 -1 -1 17 -1 -1 -1 -1 -1 -1 -1 -1 -1 -1 -1 -1 -1 -1 -1 -1 -1 -1 -1 -1 -1 -1 -1 -1 -1 -1 -1 -1 -1 -1 209 210 211 212 213 214 215 -1 -1 -1 -1 -1 -1 -1 -1 -1 -1 -1 -1 -1 -1 -1 -1 -1 -1 -1 -1 -1 -1 -1 -1 253 254 255 256 257 -1 -1 -1 -1 -1 -1 -1 -1 -1 -1 -1 -1 -1 -1 -1 -1 -1 -1 -1 -1 -1 -1 -1 -1 308 309 310 311 -1 -1 -1 -1 -1 -1 -1 -1 -1 -1 -1 -1 71 72 -1 -1 -1 -1 -1 -1 -1 -1 -1 -1 -1 -1 -1 -1 -1 -1 -1 -1 -1 -1 -1 -1 -1 -1 -1 -1 -1 -1 -1 -1 -1 -1 -1 -1 -1 -1 -1 -1 -1 -1 -1 -1 -1 -1 -1 -1 -1 -1 -1 -1 -1 -1 -1 -1 -1 -1 -1 -1 -1 -1 -1 -1 -1 -1 -1 -1 -1 -1 -1 -1 -1 -1 -1 -1 -1 -1 -1 -1 -1 -1 -1 -1 -1 -1 -1 -1 -1 -1 -1 -1 -1 -1 -1 -1 -1 -1 -1 -1 -1 -1 -1 -1 -1 -1 -1 -1 -1 -1 -1 -1 -1 -1 -1 -1 -1 -1 -1 -1 -1 -1 -1 -1 -1 -1 -1 -1 -1 -1 -1 -1 -1 -1 -1 -1 -1 -1 -1 -1 -1 -1 -1 -1 -1 -1 -1 -1 -1 -1 -1 -1 -1 -1 -1 -1 -1 -1 -1 -1 -1 -1 -1 -1 -1 -1 -1 -1 -1 -1 -1 -1 -1 -1 -1 -1 -1 -1 -1 -1 -1 -1 -1 -1 -1 -1 -1 -1 -1 -1 -1 -1 -1 -1 -1 -1 -1 -1 -1 -1 -1 -1 -1 -1 -1 -1 -1 -1 -1 -1 -1 -1 -1 -1 -1 -1 -1 -1 -1 -1 -1 -1 -1 -1 -1 -1 -1 -1 -1 -1 -1 -1 -1 -1 -1 -1 -1 -1 -1 -1 -1 -1 -1 -1 -1 -1 -1 -1 -1 -1 -1 -1 -1 -1 -1 -1 -1 -1 -1 -1 -1 -1 -1 -1 -1 -1 -1 -1 -1 -1 -1 -1 -1 -1 -1 -1 -1 -1 -1 </TopLayer>
  <CollisionLayer>-1 -1 -1 -1 1 1 1 1 1 1 1 1 -1 -1 -1 1 1 1 1 1 1 1 1 1 -1 -1 -1 -1 1 1 1 1 1 1 1 1 -1 -1 -1 -1 -1 1 1 1 1 1 1 1 -1 -1 -1 -1 1 1 1 1 1 1 1 1 -1 -1 -1 -1 -1 1 1 1 1 1 1 1 -1 -1 -1 -1 1 1 1 1 -1 1 1 1 1 -1 -1 -1 -1 1 1 1 1 1 1 1 -1 -1 -1 -1 1 1 -1 -1 -1 -1 -1 -1 -1 -1 -1 -1 -1 -1 -1 1 -1 1 -1 1 -1 -1 -1 -1 1 -1 -1 -1 -1 -1 -1 -1 -1 -1 -1 -1 -1 -1 -1 -1 -1 -1 1 1 -1 -1 -1 -1 1 -1 -1 -1 -1 -1 -1 -1 -1 -1 -1 -1 -1 -1 -1 -1 -1 -1 -1 1 -1 -1 -1 -1 1 1 1 1 1 1 1 1 -1 -1 -1 -1 -1 -1 -1 -1 -1 -1 -1 1 -1 -1 -1 -1 1 1 1 1 1 1 1 1 1 1 1 1 1 -1 -1 -1 -1 -1 -1 1 -1 -1 -1 -1 1 -1 1 1 -1 1 1 -1 1 1 1 1 1 1 1 1 1 -1 -1 1 -1 -1 -1 -1 1 1 -1 -1 -1 -1 -1 -1 1 1 1 1 1 1 1 -1 1 -1 -1 1 -1 -1 -1 -1 1 -1 -1 -1 -1 -1 -1 -1 1 1 -1 1 1 1 1 -1 1 -1 -1 -1 -1 -1 -1 -1 1 1 1 1 1 -1 -1 -1 -1 -1 -1 -1 -1 -1 -1 -1 -1 -1 -1 1 -1 -1 -1 -1 -1 -1 -1 -1 1 -1 -1 -1 -1 -1 -1 -1 -1 -1 -1 -1 -1 -1 -1 1 -1 -1 -1 -1 -1 -1 -1 -1 1 -1 -1 -1 -1 -1 -1 -1 -1 -1 -1 -1 -1 -1 -1 1 -1 -1 -1 -1 -1 -1 -1 -1 1 1 1 1 1 1 1 1 1 1 1 1 1 1 1 1 -1 -1 -1 -1 -1 -1 -1 -1 -1 -1 -1 -1 -1 -1 -1 -1 -1 -1 -1 -1 -1 -1 -1 -1 -1 -1 -1 -1 -1 -1 -1 -1 -1 -1 -1 -1 -1 -1 -1 -1 -1 -1 -1 -1 -1 -1 -1 -1 -1 -1 -1 -1 -1 -1 -1 -1 -1 -1 -1 -1 -1 -1 -1 -1 -1 -1 -1 -1 -1 -1 -1 -1 -1 -1 -1 -1 -1 -1 -1 -1 -1 -1 -1 -1 -1 -1 -1 -1 -1 -1 -1 -1 -1 -1 -1 -1 -1 -1 -1 -1 -1 -1 -1 -1 -1 -1 -1 -1 -1 -1 -1 -1 -1 -1 -1 -1 -1 -1 -1 -1 </CollisionLayer>
  <Events>
    <Event>
      <Type>ValkyrieLibrary.Events.EngineEvents.EntryPointEvent</Type>
      <Activation>16</Activation>
      <Dir>Any</Dir>
      <Location>
        <X>12</X>
        <Y>5</Y>
      </Location>
      <Size>
        <X>1</X>
        <Y>1</Y>
      </Size>
      <Parameters>
        <Parameter>
          <Name>Name</Name>
          <Value>CinnabarDestination01</Value>
        </Parameter>
      </Parameters>
    </Event>
    <Event>
      <Type>Valkyrie.Events.JumpPadEvent</Type>
      <Activation>4</Activation>
      <Dir>Any</Dir>
      <Location>
        <X>5</X>
        <Y>10</Y>
      </Location>
      <Size>
        <X>1</X>
        <Y>1</Y>
      </Size>
      <Parameters>
        <Parameter>
          <Name>DestinationName</Name>
          <Value>PalletTownEntryPoint</Value>
        </Parameter>
        <Parameter>
          <Name>Speed</Name>
          <Value>5</Value>
        </Parameter>
      </Parameters>
    </Event>
  </Events>
  <AnimatedTiles>
    <AnimatedTile>
      <TileID>55</TileID>
      <TileRect>0 160 32 32</TileRect>
      <FrameCount>7</FrameCount>
    </AnimatedTile>
  </AnimatedTiles>
</Map>